fastmcp_ai_agent_bridge/pydantic_ai/__init__.py
fastmcp_ai_agent_bridge/pydantic_ai/logging.py
fastmcp_ai_agent_bridge/pydantic_ai/tool.py
fastmcp_ai_agent_bridge/pydantic_ai/toolset.py
fastmcp_ai_agent_bridge_pydantic_ai-0.1.4.dist-info/WHEEL
fastmcp_ai_agent_bridge_pydantic_ai-0.1.4.dist-info/METADATA
fastmcp_ai_agent_bridge_pydantic_ai-0.1.4.dist-info/RECORD
